recommend_model_sdk/__init__.py
recommend_model_sdk/embeddings/__init__.py
recommend_model_sdk/embeddings/bert_embedding.py
recommend_model_sdk/embeddings/embedding_tool.py
recommend_model_sdk/embeddings/word2vec_embedding.py
recommend_model_sdk/mind_sdk/__init__.py
recommend_model_sdk/mind_sdk/experiment_enum.py
recommend_model_sdk/mind_sdk/config/__init__.py
recommend_model_sdk/mind_sdk/config/content_similar_config.py
recommend_model_sdk/mind_sdk/config/dnn_click_predictor_config.py
recommend_model_sdk/mind_sdk/config/mind_base_config.py
recommend_model_sdk/mind_sdk/dataset/__init__.py
recommend_model_sdk/mind_sdk/dataset/mind_base_dataset.py
recommend_model_sdk/mind_sdk/dataset/mind_behaviours_dataset.py
recommend_model_sdk/mind_sdk/dataset/mind_behaviours_parsed_dataset.py
recommend_model_sdk/mind_sdk/dataset/mind_news_dataset.py
recommend_model_sdk/mind_sdk/dataset/mind_user_dataset.py
recommend_model_sdk/mind_sdk/eval/__init_.py
recommend_model_sdk/mind_sdk/eval/eval_operation.py
recommend_model_sdk/mind_sdk/eval/mind_eval_tool.py
recommend_model_sdk/mind_sdk/exp/__init__.py
recommend_model_sdk/mind_sdk/exp/mind_dnn_click_predictor_train_tool.py
recommend_model_sdk/mind_sdk/model/__init__.py
recommend_model_sdk/mind_sdk/model/content_similar_model.py
recommend_model_sdk/mind_sdk/model/dnn_click_predictor.py
recommend_model_sdk/mind_sdk/train/__init__.py
recommend_model_sdk/mind_sdk/train/mind_dnn_click_predictor_train_tool.py
recommend_model_sdk/proto_class/__init__.py
recommend_model_sdk/proto_class/embedding_pb2.py
recommend_model_sdk/rank/__init__.py
recommend_model_sdk/rank/faiss_tool.py
recommend_model_sdk/rank/rank_tool.py
recommend_model_sdk/rank/time_weight_decay_tool.py
recommend_model_sdk/recommend/__init__.py
recommend_model_sdk/recommend/common_enum.py
recommend_model_sdk/recommend/rank_tool.py
recommend_model_sdk/recommend/recommend_common_util.py
recommend_model_sdk/recommend/recommend_tool.py
bytetrade_recommend_model_sdk-0.2.6.dist-info/METADATA
bytetrade_recommend_model_sdk-0.2.6.dist-info/WHEEL
bytetrade_recommend_model_sdk-0.2.6.dist-info/top_level.txt
bytetrade_recommend_model_sdk-0.2.6.dist-info/RECORD
