Metadata-Version: 2.1
Name: bytetrade-recommend-model-sdk
Version: 0.2.6
Requires-Dist: pandas (==2.0.0)
Requires-Dist: gensim (==4.3.1)
Requires-Dist: protobuf (==3.20.1)
Requires-Dist: nltk (==3.8.1)
Requires-Dist: boto3
Requires-Dist: faiss-cpu (==1.7.4)
Requires-Dist: matplotlib
Requires-Dist: rake-nltk (==1.0.6)
Requires-Dist: sentence-transformers (==2.2.2)
Requires-Dist: langdetect (==1.0.9)
Requires-Dist: weaviate-client
Requires-Dist: xgboost (==1.7.6)
Requires-Dist: imbalanced-learn (==0.11.0)
